{
  "variants": {
    "half=lower,facing=north": { "model": "thaumcraft:block/infusion_pillar", "y": 180 },
    "half=lower,facing=south": { "model": "thaumcraft:block/infusion_pillar" },
    "half=lower,facing=west":  { "model": "thaumcraft:block/infusion_pillar", "y": 90 },
    "half=lower,facing=east":  { "model": "thaumcraft:block/infusion_pillar", "y": 270 },
    "half=upper,facing=north": { "model": "thaumcraft:block/infusion_pillar_upper" },
    "half=upper,facing=south": { "model": "thaumcraft:block/infusion_pillar_upper" },
    "half=upper,facing=west":  { "model": "thaumcraft:block/infusion_pillar_upper" },
    "half=upper,facing=east":  { "model": "thaumcraft:block/infusion_pillar_upper" }
  }
}
