{
  "stage": "Stage663-682",
  "version": "6.82.0",
  "base": "Stage643-662",
  "parity_scope": [
    "Research Table shared hitbox ledger",
    "Research Note solved-note client guard",
    "Research Table visible tooltip cleanup",
    "Thaumonomicon browser raw status cleanup",
    "Thaumonomicon page/recipe debug overlay cleanup"
  ],
  "no_new_survival_mechanics": true,
  "no_new_items": true,
  "no_new_recipes": true,
  "still_not_100_percent": true,
  "honest_completion_estimate": "61-66% strict TC4 parity",
  "next_stage": "Stage683-702: Arcane Workbench + Infusion Matrix + Aura Node return pass after another Research/Thaumonomicon sweep"
}